{
"type": "FeatureCollection",
"name": "xaxx",
"crs": { "type": "name", "properties": { "name": "urn:ogc:def:crs:OGC:1.3:CRS84" } },
"features": [
{ "type": "Feature", "properties": { "id": null, "aaa": "axax", "aaada": null }, "geometry": { "type": "Point", "coordinates": [ 139.969544033893044, 35.930653450488968 ] } },
{ "type": "Feature", "properties": { "id": null, "aaa": "axAXaX", "aaada": null }, "geometry": { "type": "Point", "coordinates": [ 139.824116386513793, 35.872607067109797 ] } }
]
}
